sdtw/__init__.py
sdtw/barycenter.py
sdtw/chainer_func.py
sdtw/dataset.py
sdtw/distance.py
sdtw/path.py
sdtw/setup.py
sdtw/soft_dtw.py
sdtw/soft_dtw_fast.cpython-36m-darwin.so
soft_dtw-0.1.6.dist-info/METADATA
soft_dtw-0.1.6.dist-info/RECORD
soft_dtw-0.1.6.dist-info/WHEEL
soft_dtw-0.1.6.dist-info/top_level.txt
