Metadata-Version: 2.1
Name: soft-dtw
Version: 0.1.6
Summary: Python implementation of soft-DTW
Home-page: https://github.com/mblondel/soft-dtw/
Maintainer: Richard O'Dwyer
Maintainer-email: richard@richard.do
License: Simplified BSD
Download-URL: https://github.com/mblondel/soft-dtw/
Platform: UNKNOWN
Classifier: Intended Audience :: Science/Research
Classifier: Intended Audience :: Developers
Classifier: License :: OSI Approved
Classifier: Programming Language :: C
Classifier: Programming Language :: Python
Classifier: Topic :: Software Development
Classifier: Topic :: Scientific/Engineering
Classifier: Operating System :: Microsoft :: Windows
Classifier: Operating System :: POSIX
Classifier: Operating System :: Unix
Classifier: Operating System :: MacOS
Requires-Dist: scipy
Requires-Dist: numpy
Requires-Dist: cython
Requires-Dist: scikit-learn
Requires-Dist: chainer
